[{"id":1,"name":"沪深","subGroups":[{"id":1,"name":"沪深0","tags":[{"id":1,"name":"沪深0.标签0"}]},{"id":2,"name":"沪深1","tags":[{"id":1,"name":"沪深1.标签0"},{"id":2,"name":"沪深1.标签1"},{"id":3,"name":"沪深1.标签2"},{"id":4,"name":"沪深1.标签3"},{"id":5,"name":"沪深1.标签4"},{"id":6,"name":"沪深1.标签5"}]},{"id":3,"name":"沪深2","tags":[{"id":1,"name":"沪深2.标签0"},{"id":2,"name":"沪深2.标签1"},{"id":3,"name":"沪深2.标签2"},{"id":4,"name":"沪深2.标签3"}]}]},{"id":2,"name":"基金","subGroups":[{"id":1,"name":"基金0","tags":[{"id":1,"name":"基金0.标签0"},{"id":2,"name":"基金0.标签1"},{"id":3,"name":"基金0.标签2"},{"id":4,"name":"基金0.标签3"},{"id":5,"name":"基金0.标签4"}]},{"id":2,"name":"基金1","tags":[{"id":1,"name":"基金1.标签0"},{"id":2,"name":"基金1.标签1"},{"id":3,"name":"基金1.标签2"},{"id":4,"name":"基金1.标签3"},{"id":5,"name":"基金1.标签4"},{"id":6,"name":"基金1.标签5"}]},{"id":3,"name":"基金2","tags":[{"id":1,"name":"基金2.标签0"},{"id":2,"name":"基金2.标签1"},{"id":3,"name":"基金2.标签2"},{"id":4,"name":"基金2.标签3"},{"id":5,"name":"基金2.标签4"},{"id":6,"name":"基金2.标签5"}]},{"id":4,"name":"基金3","tags":[{"id":1,"name":"基金3.标签0"},{"id":2,"name":"基金3.标签1"}]},{"id":5,"name":"基金4","tags":[{"id":1,"name":"基金4.标签0"},{"id":2,"name":"基金4.标签1"},{"id":3,"name":"基金4.标签2"},{"id":4,"name":"基金4.标签3"},{"id":5,"name":"基金4.标签4"},{"id":6,"name":"基金4.标签5"},{"id":7,"name":"基金4.标签6"},{"id":8,"name":"基金4.标签7"},{"id":9,"name":"基金4.标签8"},{"id":10,"name":"基金4.标签9"}]},{"id":6,"name":"基金5","tags":[{"id":1,"name":"基金5.标签0"}]},{"id":7,"name":"基金6","tags":[{"id":1,"name":"基金6.标签0"},{"id":2,"name":"基金6.标签1"},{"id":3,"name":"基金6.标签2"},{"id":4,"name":"基金6.标签3"},{"id":5,"name":"基金6.标签4"},{"id":6,"name":"基金6.标签5"},{"id":7,"name":"基金6.标签6"},{"id":8,"name":"基金6.标签7"},{"id":9,"name":"基金6.标签8"},{"id":10,"name":"基金6.标签9"}]},{"id":8,"name":"基金7","tags":[{"id":1,"name":"基金7.标签0"},{"id":2,"name":"基金7.标签1"},{"id":3,"name":"基金7.标签2"},{"id":4,"name":"基金7.标签3"},{"id":5,"name":"基金7.标签4"},{"id":6,"name":"基金7.标签5"},{"id":7,"name":"基金7.标签6"},{"id":8,"name":"基金7.标签7"}]}]},{"id":3,"name":"美股I","subGroups":[{"id":1,"name":"美股I0","tags":[{"id":1,"name":"美股I0.标签0"},{"id":2,"name":"美股I0.标签1"},{"id":3,"name":"美股I0.标签2"},{"id":4,"name":"美股I0.标签3"},{"id":5,"name":"美股I0.标签4"},{"id":6,"name":"美股I0.标签5"},{"id":7,"name":"美股I0.标签6"}]}]},{"id":4,"name":"港股I","subGroups":[{"id":1,"name":"港股I0","tags":[{"id":1,"name":"港股I0.标签0"},{"id":2,"name":"港股I0.标签1"},{"id":3,"name":"港股I0.标签2"},{"id":4,"name":"港股I0.标签3"},{"id":5,"name":"港股I0.标签4"},{"id":6,"name":"港股I0.标签5"},{"id":7,"name":"港股I0.标签6"},{"id":8,"name":"港股I0.标签7"},{"id":9,"name":"港股I0.标签8"},{"id":10,"name":"港股I0.标签9"}]},{"id":2,"name":"港股I1","tags":[{"id":1,"name":"港股I1.标签0"},{"id":2,"name":"港股I1.标签1"}]},{"id":3,"name":"港股I2","tags":[{"id":1,"name":"港股I2.标签0"},{"id":2,"name":"港股I2.标签1"},{"id":3,"name":"港股I2.标签2"},{"id":4,"name":"港股I2.标签3"},{"id":5,"name":"港股I2.标签4"},{"id":6,"name":"港股I2.标签5"},{"id":7,"name":"港股I2.标签6"},{"id":8,"name":"港股I2.标签7"},{"id":9,"name":"港股I2.标签8"},{"id":10,"name":"港股I2.标签9"}]},{"id":4,"name":"港股I3","tags":[{"id":1,"name":"港股I3.标签0"},{"id":2,"name":"港股I3.标签1"},{"id":3,"name":"港股I3.标签2"},{"id":4,"name":"港股I3.标签3"}]},{"id":5,"name":"港股I4","tags":[{"id":1,"name":"港股I4.标签0"}]},{"id":6,"name":"港股I5","tags":[{"id":1,"name":"港股I5.标签0"}]},{"id":7,"name":"港股I6","tags":[{"id":1,"name":"港股I6.标签0"},{"id":2,"name":"港股I6.标签1"},{"id":3,"name":"港股I6.标签2"},{"id":4,"name":"港股I6.标签3"}]},{"id":8,"name":"港股I7","tags":[{"id":1,"name":"港股I7.标签0"},{"id":2,"name":"港股I7.标签1"},{"id":3,"name":"港股I7.标签2"},{"id":4,"name":"港股I7.标签3"},{"id":5,"name":"港股I7.标签4"},{"id":6,"name":"港股I7.标签5"},{"id":7,"name":"港股I7.标签6"}]}]},{"id":5,"name":"黄金I","subGroups":[{"id":1,"name":"黄金I0","tags":[{"id":1,"name":"黄金I0.标签0"},{"id":2,"name":"黄金I0.标签1"},{"id":3,"name":"黄金I0.标签2"},{"id":4,"name":"黄金I0.标签3"},{"id":5,"name":"黄金I0.标签4"},{"id":6,"name":"黄金I0.标签5"},{"id":7,"name":"黄金I0.标签6"}]},{"id":2,"name":"黄金I1","tags":[{"id":1,"name":"黄金I1.标签0"},{"id":2,"name":"黄金I1.标签1"},{"id":3,"name":"黄金I1.标签2"}]},{"id":3,"name":"黄金I2","tags":[{"id":1,"name":"黄金I2.标签0"}]},{"id":4,"name":"黄金I3","tags":[{"id":1,"name":"黄金I3.标签0"}]},{"id":5,"name":"黄金I4","tags":[{"id":1,"name":"黄金I4.标签0"},{"id":2,"name":"黄金I4.标签1"}]},{"id":6,"name":"黄金I5","tags":[{"id":1,"name":"黄金I5.标签0"}]},{"id":7,"name":"黄金I6","tags":[{"id":1,"name":"黄金I6.标签0"},{"id":2,"name":"黄金I6.标签1"},{"id":3,"name":"黄金I6.标签2"}]}]},{"id":6,"name":"理财","subGroups":[{"id":1,"name":"理财0","tags":[{"id":1,"name":"理财0.标签0"},{"id":2,"name":"理财0.标签1"},{"id":3,"name":"理财0.标签2"},{"id":4,"name":"理财0.标签3"},{"id":5,"name":"理财0.标签4"},{"id":6,"name":"理财0.标签5"},{"id":7,"name":"理财0.标签6"}]},{"id":2,"name":"理财1","tags":[{"id":1,"name":"理财1.标签0"},{"id":2,"name":"理财1.标签1"},{"id":3,"name":"理财1.标签2"},{"id":4,"name":"理财1.标签3"},{"id":5,"name":"理财1.标签4"},{"id":6,"name":"理财1.标签5"}]}]},{"id":7,"name":"名人财富","subGroups":[{"id":1,"name":"名人财富0","tags":[{"id":1,"name":"名人财富0.标签0"},{"id":2,"name":"名人财富0.标签1"},{"id":3,"name":"名人财富0.标签2"},{"id":4,"name":"名人财富0.标签3"},{"id":5,"name":"名人财富0.标签4"},{"id":6,"name":"名人财富0.标签5"},{"id":7,"name":"名人财富0.标签6"}]}]},{"id":8,"name":"财经段子","subGroups":[{"id":1,"name":"财经段子0","tags":[{"id":1,"name":"财经段子0.标签0"},{"id":2,"name":"财经段子0.标签1"},{"id":3,"name":"财经段子0.标签2"},{"id":4,"name":"财经段子0.标签3"},{"id":5,"name":"财经段子0.标签4"},{"id":6,"name":"财经段子0.标签5"},{"id":7,"name":"财经段子0.标签6"},{"id":8,"name":"财经段子0.标签7"}]},{"id":2,"name":"财经段子1","tags":[{"id":1,"name":"财经段子1.标签0"},{"id":2,"name":"财经段子1.标签1"},{"id":3,"name":"财经段子1.标签2"}]},{"id":3,"name":"财经段子2","tags":[{"id":1,"name":"财经段子2.标签0"},{"id":2,"name":"财经段子2.标签1"},{"id":3,"name":"财经段子2.标签2"},{"id":4,"name":"财经段子2.标签3"}]},{"id":4,"name":"财经段子3","tags":[{"id":1,"name":"财经段子3.标签0"},{"id":2,"name":"财经段子3.标签1"},{"id":3,"name":"财经段子3.标签2"}]},{"id":5,"name":"财经段子4","tags":[{"id":1,"name":"财经段子4.标签0"},{"id":2,"name":"财经段子4.标签1"},{"id":3,"name":"财经段子4.标签2"},{"id":4,"name":"财经段子4.标签3"},{"id":5,"name":"财经段子4.标签4"},{"id":6,"name":"财经段子4.标签5"},{"id":7,"name":"财经段子4.标签6"}]}]},{"id":9,"name":"消费","subGroups":[{"id":1,"name":"消费0","tags":[{"id":1,"name":"消费0.标签0"},{"id":2,"name":"消费0.标签1"},{"id":3,"name":"消费0.标签2"},{"id":4,"name":"消费0.标签3"},{"id":5,"name":"消费0.标签4"},{"id":6,"name":"消费0.标签5"},{"id":7,"name":"消费0.标签6"},{"id":8,"name":"消费0.标签7"},{"id":9,"name":"消费0.标签8"}]},{"id":2,"name":"消费1","tags":[{"id":1,"name":"消费1.标签0"},{"id":2,"name":"消费1.标签1"},{"id":3,"name":"消费1.标签2"},{"id":4,"name":"消费1.标签3"},{"id":5,"name":"消费1.标签4"}]},{"id":3,"name":"消费2","tags":[{"id":1,"name":"消费2.标签0"},{"id":2,"name":"消费2.标签1"},{"id":3,"name":"消费2.标签2"},{"id":4,"name":"消费2.标签3"},{"id":5,"name":"消费2.标签4"},{"id":6,"name":"消费2.标签5"},{"id":7,"name":"消费2.标签6"},{"id":8,"name":"消费2.标签7"},{"id":9,"name":"消费2.标签8"}]},{"id":4,"name":"消费3","tags":[{"id":1,"name":"消费3.标签0"},{"id":2,"name":"消费3.标签1"},{"id":3,"name":"消费3.标签2"},{"id":4,"name":"消费3.标签3"},{"id":5,"name":"消费3.标签4"},{"id":6,"name":"消费3.标签5"},{"id":7,"name":"消费3.标签6"},{"id":8,"name":"消费3.标签7"}]},{"id":5,"name":"消费4","tags":[{"id":1,"name":"消费4.标签0"},{"id":2,"name":"消费4.标签1"},{"id":3,"name":"消费4.标签2"},{"id":4,"name":"消费4.标签3"},{"id":5,"name":"消费4.标签4"},{"id":6,"name":"消费4.标签5"},{"id":7,"name":"消费4.标签6"},{"id":8,"name":"消费4.标签7"},{"id":9,"name":"消费4.标签8"},{"id":10,"name":"消费4.标签9"}]},{"id":6,"name":"消费5","tags":[{"id":1,"name":"消费5.标签0"},{"id":2,"name":"消费5.标签1"},{"id":3,"name":"消费5.标签2"},{"id":4,"name":"消费5.标签3"},{"id":5,"name":"消费5.标签4"},{"id":6,"name":"消费5.标签5"},{"id":7,"name":"消费5.标签6"},{"id":8,"name":"消费5.标签7"}]},{"id":7,"name":"消费6","tags":[{"id":1,"name":"消费6.标签0"},{"id":2,"name":"消费6.标签1"},{"id":3,"name":"消费6.标签2"},{"id":4,"name":"消费6.标签3"},{"id":5,"name":"消费6.标签4"},{"id":6,"name":"消费6.标签5"},{"id":7,"name":"消费6.标签6"},{"id":8,"name":"消费6.标签7"}]},{"id":8,"name":"消费7","tags":[{"id":1,"name":"消费7.标签0"},{"id":2,"name":"消费7.标签1"},{"id":3,"name":"消费7.标签2"},{"id":4,"name":"消费7.标签3"},{"id":5,"name":"消费7.标签4"},{"id":6,"name":"消费7.标签5"},{"id":7,"name":"消费7.标签6"},{"id":8,"name":"消费7.标签7"},{"id":9,"name":"消费7.标签8"},{"id":10,"name":"消费7.标签9"}]},{"id":9,"name":"消费8","tags":[{"id":1,"name":"消费8.标签0"},{"id":2,"name":"消费8.标签1"},{"id":3,"name":"消费8.标签2"},{"id":4,"name":"消费8.标签3"},{"id":5,"name":"消费8.标签4"}]},{"id":10,"name":"消费9","tags":[{"id":1,"name":"消费9.标签0"},{"id":2,"name":"消费9.标签1"},{"id":3,"name":"消费9.标签2"},{"id":4,"name":"消费9.标签3"},{"id":5,"name":"消费9.标签4"},{"id":6,"name":"消费9.标签5"},{"id":7,"name":"消费9.标签6"},{"id":8,"name":"消费9.标签7"}]}]},{"id":10,"name":"国际I","subGroups":[{"id":1,"name":"国际I0","tags":[{"id":1,"name":"国际I0.标签0"},{"id":2,"name":"国际I0.标签1"},{"id":3,"name":"国际I0.标签2"},{"id":4,"name":"国际I0.标签3"},{"id":5,"name":"国际I0.标签4"},{"id":6,"name":"国际I0.标签5"},{"id":7,"name":"国际I0.标签6"}]},{"id":2,"name":"国际I1","tags":[{"id":1,"name":"国际I1.标签0"},{"id":2,"name":"国际I1.标签1"},{"id":3,"name":"国际I1.标签2"},{"id":4,"name":"国际I1.标签3"},{"id":5,"name":"国际I1.标签4"},{"id":6,"name":"国际I1.标签5"},{"id":7,"name":"国际I1.标签6"}]},{"id":3,"name":"国际I2","tags":[{"id":1,"name":"国际I2.标签0"},{"id":2,"name":"国际I2.标签1"},{"id":3,"name":"国际I2.标签2"},{"id":4,"name":"国际I2.标签3"},{"id":5,"name":"国际I2.标签4"},{"id":6,"name":"国际I2.标签5"},{"id":7,"name":"国际I2.标签6"},{"id":8,"name":"国际I2.标签7"},{"id":9,"name":"国际.王程凯"}]}]}]